khorosjx/__init__.py
khorosjx/admin.py
khorosjx/content.py
khorosjx/core.py
khorosjx/groups.py
khorosjx/spaces.py
khorosjx/users.py
khorosjx/errors/__init__.py
khorosjx/errors/exceptions.py
khorosjx/utils/__init__.py
khorosjx/utils/classes.py
khorosjx/utils/core_utils.py
khorosjx-1.0.0.dist-info/LICENSE
khorosjx-1.0.0.dist-info/METADATA
khorosjx-1.0.0.dist-info/WHEEL
khorosjx-1.0.0.dist-info/top_level.txt
khorosjx-1.0.0.dist-info/RECORD
