Metadata-Version: 2.1
Name: khorosjx
Version: 1.0.0
Summary: Useful tools and utilities to assist in managing a Khoros JX (formerly Jive-x) or Jive-n community.
Home-page: https://github.com/jeffshurtliff/khorosjx
Author: Jeff Shurtliff
Author-email: jeff.shurtliff@rsa.com
License: UNKNOWN
Platform: UNKNOWN
Classifier: Development Status :: 3 - Alpha
Classifier: Environment :: Web Environment
Classifier: Intended Audience :: Information Technology
Classifier: Intended Audience :: System Administrators
Classifier: License :: Freely Distributable
Classifier: Natural Language :: English
Classifier: Operating System :: OS Independent
Classifier: Programming Language :: Python :: 3
Classifier: Topic :: Communications
Classifier: Topic :: Internet :: WWW/HTTP :: Dynamic Content :: Content Management System
Classifier: Topic :: Internet :: WWW/HTTP :: Dynamic Content :: Message Boards
Classifier: Topic :: Internet :: WWW/HTTP :: Site Management
Requires-Python: >=3.6
